stackone_ai/__init__.py
stackone_ai/constants.py
stackone_ai/models.py
stackone_ai/toolset.py
stackone_ai/utility_tools.py
stackone_ai/feedback/__init__.py
stackone_ai/feedback/tool.py
stackone_ai/integrations/__init__.py
stackone_ai/integrations/langgraph.py
stackone_ai/utils/__init__.py
stackone_ai/utils/tfidf_index.py
stackone_ai/py.typed
stackone_ai-2.3.1.dist-info/METADATA
stackone_ai-2.3.1.dist-info/WHEEL
stackone_ai-2.3.1.dist-info/licenses/LICENSE
stackone_ai-2.3.1.dist-info/RECORD
