Metadata-Version: 2.4
Name: stackone-ai
Version: 2.3.1
Summary: agents performing actions on your SaaS
Author-email: StackOne <support@stackone.com>
License-File: LICENSE
Classifier: Development Status :: 4 - Beta
Classifier: Intended Audience :: Developers
Classifier: License :: OSI Approved :: MIT License
Classifier: Programming Language :: Python :: 3
Classifier: Programming Language :: Python :: 3.10
Classifier: Programming Language :: Python :: 3.11
Classifier: Programming Language :: Python :: 3.12
Classifier: Programming Language :: Python :: 3.13
Classifier: Topic :: Software Development :: Libraries :: Python Modules
Requires-Python: >=3.10
Requires-Dist: bm25s>=0.2.2
Requires-Dist: httpx>=0.28.0
Requires-Dist: langchain-core>=0.1.0
Requires-Dist: numpy>=1.24.0
Requires-Dist: pydantic>=2.10.6
Requires-Dist: typing-extensions>=4.0.0
Provides-Extra: examples
Requires-Dist: crewai>=0.102.0; extra == 'examples'
Requires-Dist: langchain-openai>=0.3.6; extra == 'examples'
Requires-Dist: langgraph>=0.2.0; extra == 'examples'
Requires-Dist: openai>=1.63.2; extra == 'examples'
Requires-Dist: python-dotenv>=1.0.1; extra == 'examples'
Provides-Extra: mcp
Requires-Dist: mcp>=1.3.0; extra == 'mcp'
